{"meta":{"generator":"0.0.1","format":19},"custom":{"Getting Started":{"name":"Getting Started","files":{"GettingStarted":{"name":"Getting Started","type":"md","content":"## Getting Started\n\nplaceholder","path":"guides/Getting Started/GettingStarted.md"}}}},"classes":[{"name":"TagsClient","description":"The client for handling everything. See {@tutorial GettingStarted} for more information how to get started using this class.","extends":["external:KlasaClient"],"construct":{"name":"TagsClient","description":"Constructs the tags client","params":[{"name":"config","description":"The config to pass to the new client","optional":true,"type":[[["external:KlasaClientOptions"]]]}]},"meta":{"line":13,"file":"Client.js","path":"dist/lib"}}],"typedefs":[],"externals":[{"name":"KlasaClient","see":["{@link https://klasa.js.org/#/docs/klasa/master/class/KlasaClient}"],"meta":{"line":9,"file":"index.js","path":"dist"}},{"name":"KlasaClientOptions","see":["{@link https://klasa.js.org/#/docs/klasa/master/typedef/KlasaClientOptions}"],"meta":{"line":13,"file":"index.js","path":"dist"}}]}